corda/__init__.py
corda/_version.py
corda/benchmark.py
corda/corda.py
corda/util.py
corda/data/cemet.xml
corda-0.5.1.dist-info/LICENSE
corda-0.5.1.dist-info/METADATA
corda-0.5.1.dist-info/WHEEL
corda-0.5.1.dist-info/top_level.txt
corda-0.5.1.dist-info/RECORD
