Metadata-Version: 2.1
Name: corda
Version: 0.5.1
Summary: Genome-scale model construction with CORDA
Home-page: https://github.com/cdiener/corda
Author: Christian Diener
Author-email: mail@cdiener.com
License: MIT
Keywords: biology metabolism reconstruction cobra
Platform: UNKNOWN
Classifier: Development Status :: 3 - Alpha
Classifier: Intended Audience :: Science/Research
Classifier: Topic :: Scientific/Engineering :: Bio-Informatics
Classifier: License :: OSI Approved :: MIT License
Classifier: Programming Language :: Python :: 3
Classifier: Programming Language :: Python :: 3.4
Classifier: Programming Language :: Python :: 3.5
Requires-Dist: cobra (>=0.25.0)
Requires-Dist: numpy (>=1.10.0)
Provides-Extra: dev
Requires-Dist: check-manifest ; extra == 'dev'
Provides-Extra: test
Requires-Dist: coverage ; extra == 'test'
